{
  "products": [
    {
      "name": "sản phẩm mới nhất update 10 vạn lần",
      "image": "https://res.cloudinary.com/dkrifqhuk/image/upload/v1654924637/asm/IMG_8300_ncekhq.jpg",
      "desc": "Để nói về sự phong phóng hay giàu có trong ẩm thực thì Mỹ không được đánh giá cao dù trong ẩm thực châu Âu hay châu Á. Tuy nhiên, cũng không thể bỏ qua ẩm thực Mỹ được, bởi nó có sự đặc biệt và khác biệt khiến nhiều người phải trầm trồ.",
      "id": 9
    }
  ],
  "users": [
    {
      "email": "giang113@gmail.com",
      "password": "$2a$10$.N85r.eYOGH/481ui2ZQZejOAVW.Rf/OnEs.xzD7zmEUqpDURqNty",
      "name": "Giang 69",
      "id": 1
    },
    {
      "email": "giangqu13579@gmail.com",
      "password": "$2a$10$lXMKI4TwPSBUsSrFPq3ZNOYn1/0GqpDrObct5EEZbTEx4O8VTbZIy",
      "name": "Product A",
      "id": 2
    }
  ]
}